sgs2.py
sgs2-0.1.1.dist-info/LICENSE
sgs2-0.1.1.dist-info/METADATA
sgs2-0.1.1.dist-info/WHEEL
sgs2-0.1.1.dist-info/RECORD
