Metadata-Version: 2.3
Name: sgs2
Version: 0.1.1
Summary: A pure Python interface for the Brazilian Central Bank's Time Series Management System (SGS) API
License: MIT
Author: Renan Moretto
Author-email: renan_moretto@outlook.com
Requires-Python: >=3.9
Classifier: License :: OSI Approved :: MIT License
Classifier: Programming Language :: Python :: 3
Classifier: Programming Language :: Python :: 3.9
Classifier: Programming Language :: Python :: 3.10
Classifier: Programming Language :: Python :: 3.11
Classifier: Programming Language :: Python :: 3.12
Classifier: Programming Language :: Python :: 3.13
Requires-Dist: beautifulsoup4 (>=4.13.3)
Requires-Dist: pandas (>=2.2.3,<3.0.0)
Requires-Dist: requests (>=2.32.3,<3.0.0)
